.gitlab-ci.yml
.travis.yml
CHANGES.rst
CONTRIBUTORS.rst
DEVELOP.rst
LICENSE.GPL
LICENSE.rst
MANIFEST.in
README.rst
requirements.txt
setup.cfg
setup.py
docs/index.rst
src/collective/__init__.py
src/collective.behavior.altimage.egg-info/PKG-INFO
src/collective.behavior.altimage.egg-info/SOURCES.txt
src/collective.behavior.altimage.egg-info/dependency_links.txt
src/collective.behavior.altimage.egg-info/entry_points.txt
src/collective.behavior.altimage.egg-info/namespace_packages.txt
src/collective.behavior.altimage.egg-info/not-zip-safe
src/collective.behavior.altimage.egg-info/requires.txt
src/collective.behavior.altimage.egg-info/top_level.txt
src/collective/behavior/__init__.py
src/collective/behavior/altimage/__init__.py
src/collective/behavior/altimage/altimage.pt
src/collective/behavior/altimage/behavior.py
src/collective/behavior/altimage/browser.py
src/collective/behavior/altimage/configure.zcml
src/collective/behavior/altimage/indexers.py
src/collective/behavior/altimage/interfaces.py
src/collective/behavior/altimage/permissions.zcml
src/collective/behavior/altimage/setuphandlers.py
src/collective/behavior/altimage/testing.py
src/collective/behavior/altimage/upgrades.py
src/collective/behavior/altimage/upgrades.zcml
src/collective/behavior/altimage/locales/README.rst
src/collective/behavior/altimage/locales/__init__.py
src/collective/behavior/altimage/locales/collective.behavior.altimage.pot
src/collective/behavior/altimage/locales/update.py
src/collective/behavior/altimage/locales/update.sh
src/collective/behavior/altimage/locales/en/LC_MESSAGES/collective.behavior.altimage.mo
src/collective/behavior/altimage/locales/en/LC_MESSAGES/collective.behavior.altimage.po
src/collective/behavior/altimage/profiles/default/browserlayer.xml
src/collective/behavior/altimage/profiles/default/catalog.xml
src/collective/behavior/altimage/profiles/default/metadata.xml
src/collective/behavior/altimage/profiles/default/registry.xml
src/collective/behavior/altimage/profiles/default/rolemap.xml
src/collective/behavior/altimage/profiles/uninstall/browserlayer.xml
src/collective/behavior/altimage/tests/__init__.py
src/collective/behavior/altimage/tests/test_behavior_alt_image.py
src/collective/behavior/altimage/tests/test_robot.py
src/collective/behavior/altimage/tests/test_setup.py
src/collective/behavior/altimage/tests/robot/test_example.robot