Metadata-Version: 2.1
Name: collective.behavior.altimage
Version: 1.0.0b1
Summary: Plone behavior for adding an alternative image, next to the lead image
Home-page: https://github.com/collective/collective.behavior.altimage
Author: Maurits van Rees
Author-email: m.van.rees@zestsoftware.nl
License: GPL version 2
Keywords: Python Plone
Platform: UNKNOWN
Classifier: Development Status :: 4 - Beta
Classifier: Environment :: Web Environment
Classifier: Framework :: Plone
Classifier: Framework :: Plone :: 5.0
Classifier: Framework :: Plone :: 5.1
Classifier: Programming Language :: Python
Classifier: Programming Language :: Python :: 2.7
Classifier: Operating System :: OS Independent
Classifier: License :: OSI Approved :: GNU General Public License v2 (GPLv2)
Provides-Extra: test
